ceeder/__init__.py
ceeder/cdr.py
ceeder/ceeder.py
ceeder/schemas/__init__.py
ceeder/schemas/cdr-v4.json
ceeder/schemas/cdr-v5.json
ceeder/zipper.py
ceeder-1.2.0.dist-info/LICENSE
ceeder-1.2.0.dist-info/WHEEL
ceeder-1.2.0.dist-info/METADATA
ceeder-1.2.0.dist-info/RECORD
