Metadata-Version: 2.1
Name: ceeder
Version: 1.2.0
Summary: Library for working with CDR files and analytics.
Home-page: https://github.com/qntfy/ceeder
License: MIT
Keywords: ceeder,cdr
Author: max thomas
Author-email: max@qntfy.com
Classifier: License :: OSI Approved :: MIT License
Classifier: Programming Language :: Python :: 2
Classifier: Programming Language :: Python :: 2.7
Classifier: Programming Language :: Python :: 3
Classifier: Programming Language :: Python :: 3.4
Classifier: Programming Language :: Python :: 3.5
Classifier: Programming Language :: Python :: 3.6
Classifier: Programming Language :: Python :: 3.7
Classifier: Programming Language :: Python :: 3.8
Requires-Dist: falcon (>=2.0.0,<3.0.0)
Requires-Dist: jsonschema (>=3.2.0,<4.0.0)
Project-URL: Repository, https://github.com/qntfy/ceeder
